lca_algebraic/__init__.py
lca_algebraic/activity.py
lca_algebraic/axis_dict.py
lca_algebraic/base_utils.py
lca_algebraic/cache.py
lca_algebraic/database.py
lca_algebraic/db.py
lca_algebraic/explore.py
lca_algebraic/globals.py
lca_algebraic/globs.py
lca_algebraic/helpers.py
lca_algebraic/interpolation.py
lca_algebraic/io.py
lca_algebraic/lca.py
lca_algebraic/log.py
lca_algebraic/methods.py
lca_algebraic/oie.py
lca_algebraic/params.py
lca_algebraic/settings.py
lca_algebraic/stats.py
lca_algebraic/units.py
lca_algebraic_inventory_loops-1.2.2385221.dev0.dist-info/LICENSE
lca_algebraic_inventory_loops-1.2.2385221.dev0.dist-info/METADATA
lca_algebraic_inventory_loops-1.2.2385221.dev0.dist-info/WHEEL
lca_algebraic_inventory_loops-1.2.2385221.dev0.dist-info/top_level.txt
lca_algebraic_inventory_loops-1.2.2385221.dev0.dist-info/RECORD
