Metadata-Version: 2.1
Name: lca_algebraic_inventory-loops
Version: 1.2.2385221.dev0
Summary: This library provides a layer above brightway2 for defining parametric models and running super fast LCA for monte carlo analysis.
Home-page: https://lca-algebraic.readthedocs.io/en/stable/
Author: OIE - Mines ParisTech
Author-email: raphael.jolivet@mines-paristech.fr
License: BSD
Project-URL: Homepage, https://github.com/oie-mines-paristech/lca_algebraic
Project-URL: Repository, https://github.com/oie-mines-paristech/lca_algebraic.git
Project-URL: Documentation, https://lca-algebraic.readthedocs.io/
Project-URL: Changelog, https://github.com/oie-mines-paristech/lca_algebraic/blob/main/RELEASE_NOTES.md
Keywords: LCA brightway2 monte-carlo parametric
License-File: LICENSE
Requires-Dist: tabulate
Requires-Dist: ipywidgets
Requires-Dist: pandas
Requires-Dist: pyarrow
Requires-Dist: seaborn
Requires-Dist: sympy
Requires-Dist: matplotlib
Requires-Dist: deprecation
Requires-Dist: brightway2
Requires-Dist: SALib
Requires-Dist: pint
Requires-Dist: typing-extensions
Requires-Dist: pypardiso
